moraikit/__init__.py
moraikit/sensor.py
moraikit/sim_adapter.py
moraikit/types.py
moraikit/common_utils/__init__.py
moraikit/common_utils/compress_utils.py
moraikit/common_utils/transformation.py
moraikit/protobuf/__init__.py
moraikit/protobuf/conversions.py
moraikit/protobuf/morai_actor_pb2.py
moraikit/protobuf/morai_actor_pb2_grpc.py
moraikit/protobuf/morai_mgeo_pb2.py
moraikit/protobuf/morai_mgeo_pb2_grpc.py
moraikit/protobuf/morai_sensor_pb2.py
moraikit/protobuf/morai_sensor_pb2_grpc.py
moraikit/protobuf/morai_sim_info_pb2.py
moraikit/protobuf/morai_sim_info_pb2_grpc.py
moraikit/protobuf/morai_simulation_pb2.py
moraikit/protobuf/morai_simulation_pb2_grpc.py
moraikit/protobuf/morai_type_pb2.py
moraikit/protobuf/morai_type_pb2_grpc.py
morai_kit-1.1.0.dist-info/METADATA
morai_kit-1.1.0.dist-info/WHEEL
morai_kit-1.1.0.dist-info/top_level.txt
morai_kit-1.1.0.dist-info/RECORD
