Metadata-Version: 2.1
Name: morai-kit
Version: 1.1.0
Summary: MORAI Sensor Kit
Author: ischoi
Author-email: ischoi@morai.ai
Classifier: Programming Language :: Python :: 3
Classifier: License :: OSI Approved :: MIT License
Classifier: Operating System :: OS Independent
Requires-Python: >=3.6
Requires-Dist: grpcio (==1.44.0)
Requires-Dist: grpcio-tools (==1.44.0)
Requires-Dist: numpy
Requires-Dist: spatialmath-python (==1.0.3)
